README.md
setup.py
bin/hdd-stat
system_status_server/__init__.py
system_status_server/app.py
system_status_server/cpuprovider.py
system_status_server/dataproviderbase.py
system_status_server/hddprovider.py
system_status_server/httphandler.py
system_status_server/infodaemon.py
system_status_server/loadprovider.py
system_status_server/memoryprovider.py
system_status_server/uptimeprovider.py
system_status_server.egg-info/PKG-INFO
system_status_server.egg-info/SOURCES.txt
system_status_server.egg-info/dependency_links.txt
system_status_server.egg-info/requires.txt
system_status_server.egg-info/top_level.txt