Metadata-Version: 1.0
Name: system-status-server
Version: 2.0.1
Summary: This is a very lightweight stuff to get some system status info in JSON.
Home-page: https://github.com/voidpp/system-status-server
Author: Lajos Santa
Author-email: santa.lajos@coldline.hu
License: MIT
Platform: UNKNOWN
